MANIFEST.in
README.rst
setup.py
django_netaxept.egg-info/PKG-INFO
django_netaxept.egg-info/SOURCES.txt
django_netaxept.egg-info/dependency_links.txt
django_netaxept.egg-info/not-zip-safe
django_netaxept.egg-info/requires.txt
django_netaxept.egg-info/top_level.txt
djnetaxept/__init__.py
djnetaxept/admin.py
djnetaxept/exceptions.py
djnetaxept/managers.py
djnetaxept/models.py
djnetaxept/operations.py
djnetaxept/utils.py
djnetaxept/test_utils/__init__.py
djnetaxept/test_utils/cli.py