Metadata-Version: 1.1
Name: django-netaxept
Version: 1.0
Summary: This is a generic payment app for django using Netaxept
Home-page: http://github.com/fivethreeo/django-netaxept/
Author: Oyvind Saltvik
Author-email: oyvind.saltvik@gmail.com
License: UNKNOWN
Platform: UNKNOWN
Classifier: Development Status :: 4 - Beta
Classifier: Environment :: Web Environment
Classifier: Intended Audience :: Developers
Classifier: License :: OSI Approved :: BSD License
Classifier: Operating System :: OS Independent
Classifier: Programming Language :: Python
Classifier: Framework :: Django
